evox/__init__.py
evox/algorithms/__init__.py
evox/algorithms/mo/__init__.py
evox/algorithms/mo/hype.py
evox/algorithms/mo/moead.py
evox/algorithms/mo/nsga2.py
evox/algorithms/mo/nsga3.py
evox/algorithms/mo/rvea.py
evox/algorithms/mo/rveaa.py
evox/algorithms/so/__init__.py
evox/algorithms/so/de_variants/__init__.py
evox/algorithms/so/de_variants/code.py
evox/algorithms/so/de_variants/de.py
evox/algorithms/so/de_variants/jade.py
evox/algorithms/so/de_variants/ode.py
evox/algorithms/so/de_variants/sade.py
evox/algorithms/so/de_variants/shade.py
evox/algorithms/so/es_variants/__init__.py
evox/algorithms/so/es_variants/adam_step.py
evox/algorithms/so/es_variants/ars.py
evox/algorithms/so/es_variants/asebo.py
evox/algorithms/so/es_variants/cma_es.py
evox/algorithms/so/es_variants/des.py
evox/algorithms/so/es_variants/esmc.py
evox/algorithms/so/es_variants/guided_es.py
evox/algorithms/so/es_variants/nes.py
evox/algorithms/so/es_variants/noise_reuse_es.py
evox/algorithms/so/es_variants/open_es.py
evox/algorithms/so/es_variants/persistent_es.py
evox/algorithms/so/es_variants/snes.py
evox/algorithms/so/es_variants/sort_utils.py
evox/algorithms/so/pso_variants/__init__.py
evox/algorithms/so/pso_variants/clpso.py
evox/algorithms/so/pso_variants/cso.py
evox/algorithms/so/pso_variants/dms_pso_el.py
evox/algorithms/so/pso_variants/fs_pso.py
evox/algorithms/so/pso_variants/pso.py
evox/algorithms/so/pso_variants/sl_pso_gs.py
evox/algorithms/so/pso_variants/sl_pso_us.py
evox/algorithms/so/pso_variants/utils.py
evox/core/__init__.py
evox/core/components.py
evox/core/module.py
evox/metrics/__init__.py
evox/metrics/gd.py
evox/metrics/hv.py
evox/metrics/igd.py
evox/operators/__init__.py
evox/operators/crossover/__init__.py
evox/operators/crossover/differential_evolution.py
evox/operators/crossover/sbx.py
evox/operators/crossover/sbx_half.py
evox/operators/mutation/__init__.py
evox/operators/mutation/pm_mutation.py
evox/operators/sampling/__init__.py
evox/operators/sampling/gird.py
evox-1.3.0.dist-info/licenses/LICENSE
evox-1.3.0.dist-info/METADATA
evox-1.3.0.dist-info/WHEEL
evox-1.3.0.dist-info/top_level.txt
evox-1.3.0.dist-info/RECORD
