Metadata-Version: 2.4
Name: evox
Version: 1.3.0
Summary: evox
Author-email: Bill Huang <bill.huang2001@gmail.com>, Boqing Xu <xuboqing123@gmail.com>, Christina Lee <1315552992@qq.com>, Kevin Sun <skk7757@163.com>, Yanchen Li <48726053+liyc5929@users.noreply.github.com>, Zhenyu Liang <zhenyuliang97@gmail.com>
License-Expression: GPL-3.0-or-later
Project-URL: Homepage, https://github.com/EMI-Group/evox
Project-URL: Bug Tracker, https://github.com/EMI-Group/evox/issues
Classifier: Programming Language :: Python :: 3
Classifier: Intended Audience :: Science/Research
Classifier: Topic :: Scientific/Engineering :: Artificial Intelligence
Requires-Python: >=3.10
License-File: LICENSE
Requires-Dist: torch>=2.6.0
Requires-Dist: numpy>=2.0.0
Provides-Extra: vis
Requires-Dist: plotly>=5.0.0; extra == "vis"
Requires-Dist: pandas>=2.0.0; extra == "vis"
Provides-Extra: neuroevolution
Requires-Dist: torchvision>=0.16.0; extra == "neuroevolution"
Requires-Dist: brax>=0.12.0; extra == "neuroevolution"
Requires-Dist: playground>=0.0.4; extra == "neuroevolution"
Requires-Dist: imageio>=2.0.0; extra == "neuroevolution"
Provides-Extra: test
Requires-Dist: torchvision>=0.16.0; extra == "test"
Requires-Dist: brax>=0.12.0; extra == "test"
Requires-Dist: plotly>=5.0.0; extra == "test"
Requires-Dist: playground>=0.0.4; extra == "test"
Requires-Dist: imageio>=2.0.0; extra == "test"
Provides-Extra: docs
Requires-Dist: shibuya; extra == "docs"
Requires-Dist: sphinx-autodoc2; extra == "docs"
Requires-Dist: sphinx; extra == "docs"
Requires-Dist: nbsphinx; extra == "docs"
Requires-Dist: myst-nb; extra == "docs"
Requires-Dist: ipython; extra == "docs"
Requires-Dist: myst-parser[linkify]; extra == "docs"
Requires-Dist: sphinx_copybutton; extra == "docs"
Requires-Dist: sphinx_design; extra == "docs"
Requires-Dist: sphinx-favicon; extra == "docs"
Requires-Dist: sphinxcontrib-mermaid; extra == "docs"
Requires-Dist: polib; extra == "docs"
Provides-Extra: default
Requires-Dist: plotly>=5.0.0; extra == "default"
Requires-Dist: pandas>=2.0.0; extra == "default"
Dynamic: license-file
